sourcemap_cli/__init__.py
sourcemap_cli/__main__.py
sourcemap_cli/api.py
sourcemap_cli/cli.py
sourcemap_cli/entrypoint.py
sourcemap_cli/io_handler.py
sourcemap_cli/models.py
sourcemap_cli/parser.py
sourcemap_cli/ranking.py
sourcemap_cli/renderer.py
sourcemap_cli/repomap.py
sourcemap_cli/tui_app.py
sourcemap_cli/waiting.py
sourcemap_cli/queries/tree-sitter-language-pack/README.md
sourcemap_cli/queries/tree-sitter-language-pack/arduino-tags.scm
sourcemap_cli/queries/tree-sitter-language-pack/c-tags.scm
sourcemap_cli/queries/tree-sitter-language-pack/chatito-tags.scm
sourcemap_cli/queries/tree-sitter-language-pack/clojure-tags.scm
sourcemap_cli/queries/tree-sitter-language-pack/commonlisp-tags.scm
sourcemap_cli/queries/tree-sitter-language-pack/cpp-tags.scm
sourcemap_cli/queries/tree-sitter-language-pack/csharp-tags.scm
sourcemap_cli/queries/tree-sitter-language-pack/d-tags.scm
sourcemap_cli/queries/tree-sitter-language-pack/dart-tags.scm
sourcemap_cli/queries/tree-sitter-language-pack/elisp-tags.scm
sourcemap_cli/queries/tree-sitter-language-pack/elixir-tags.scm
sourcemap_cli/queries/tree-sitter-language-pack/elm-tags.scm
sourcemap_cli/queries/tree-sitter-language-pack/gleam-tags.scm
sourcemap_cli/queries/tree-sitter-language-pack/go-tags.scm
sourcemap_cli/queries/tree-sitter-language-pack/java-tags.scm
sourcemap_cli/queries/tree-sitter-language-pack/javascript-tags.scm
sourcemap_cli/queries/tree-sitter-language-pack/lua-tags.scm
sourcemap_cli/queries/tree-sitter-language-pack/matlab-tags.scm
sourcemap_cli/queries/tree-sitter-language-pack/ocaml-tags.scm
sourcemap_cli/queries/tree-sitter-language-pack/ocaml_interface-tags.scm
sourcemap_cli/queries/tree-sitter-language-pack/pony-tags.scm
sourcemap_cli/queries/tree-sitter-language-pack/properties-tags.scm
sourcemap_cli/queries/tree-sitter-language-pack/python-tags.scm
sourcemap_cli/queries/tree-sitter-language-pack/r-tags.scm
sourcemap_cli/queries/tree-sitter-language-pack/racket-tags.scm
sourcemap_cli-0.5.0.dist-info/METADATA
sourcemap_cli-0.5.0.dist-info/WHEEL
sourcemap_cli-0.5.0.dist-info/entry_points.txt
sourcemap_cli-0.5.0.dist-info/licenses/LICENSE
sourcemap_cli-0.5.0.dist-info/RECORD
