Metadata-Version: 2.4
Name: sourcemap-cli
Version: 0.5.0
Summary: A tool for generating intelligent repository maps showing code structure and relationships
Project-URL: Homepage, https://github.com/BumpyClock/repomap
Project-URL: Documentation, https://github.com/BumpyClock/repomap#readme
Project-URL: Repository, https://github.com/BumpyClock/repomap.git
Project-URL: Issues, https://github.com/BumpyClock/repomap/issues
Author: Aditya Sharma
License: MIT
License-File: LICENSE
Keywords: analysis,ast,code,map,repository,tree-sitter
Classifier: Development Status :: 4 - Beta
Classifier: Environment :: Console
Classifier: Intended Audience :: Developers
Classifier: License :: OSI Approved :: MIT License
Classifier: Operating System :: OS Independent
Classifier: Programming Language :: Python :: 3
Classifier: Programming Language :: Python :: 3.8
Classifier: Programming Language :: Python :: 3.9
Classifier: Programming Language :: Python :: 3.10
Classifier: Programming Language :: Python :: 3.11
Classifier: Programming Language :: Python :: 3.12
Classifier: Topic :: Software Development :: Documentation
Classifier: Topic :: Software Development :: Libraries :: Python Modules
Classifier: Topic :: Text Processing :: Linguistic
Requires-Python: >=3.11
Requires-Dist: diskcache>=5.6.3
Requires-Dist: grep-ast>=0.9.0
Requires-Dist: networkx>=3.5
Requires-Dist: pygments>=2.19.2
Requires-Dist: pyperclip>=1.8.0
Requires-Dist: rich>=13.7.0
Requires-Dist: scipy>=1.16.0
Requires-Dist: textual>=5.3.0
Requires-Dist: tqdm>=4.67.1
Requires-Dist: typer>=0.12.5
Provides-Extra: dev
Requires-Dist: black>=25.1.0; extra == 'dev'
Requires-Dist: pytest-cov>=6.2.1; extra == 'dev'
Requires-Dist: pytest>=8.4.1; extra == 'dev'
Requires-Dist: ruff>=0.12.4; extra == 'dev'
